bflogoreplacer/__init__.py
bflogoreplacer/common.py
bflogoreplacer/replacer.py
bflogoreplacer-0.2.0.data/scripts/bflogoreplacer
bflogoreplacer-0.2.0.dist-info/METADATA
bflogoreplacer-0.2.0.dist-info/RECORD
bflogoreplacer-0.2.0.dist-info/WHEEL
bflogoreplacer-0.2.0.dist-info/top_level.txt
