Metadata-Version: 2.1
Name: bflogoreplacer
Version: 0.2.0
Summary: Tools for customizing the logo in a Betaflight OSD font
Home-page: https://github.com/atomgomba/bflogoreplacer
Author: Károly Kiripolszky
Author-email: karcsi@ekezet.com
License: GPLv3
Platform: UNKNOWN
